MANIFEST.in
README.txt
setup.cfg
setup.py
docs/HISTORY.txt
docs/HISTORY.txt~
docs/INSTALL.txt
docs/LICENSE.GPL
docs/LICENSE.txt
quintagroup/__init__.py
quintagroup.canonicalpath.egg-info/PKG-INFO
quintagroup.canonicalpath.egg-info/SOURCES.txt
quintagroup.canonicalpath.egg-info/dependency_links.txt
quintagroup.canonicalpath.egg-info/entry_points.txt
quintagroup.canonicalpath.egg-info/namespace_packages.txt
quintagroup.canonicalpath.egg-info/not-zip-safe
quintagroup.canonicalpath.egg-info/requires.txt
quintagroup.canonicalpath.egg-info/top_level.txt
quintagroup/canonicalpath/README.txt
quintagroup/canonicalpath/__init__.py
quintagroup/canonicalpath/adapters.py
quintagroup/canonicalpath/catalog.py
quintagroup/canonicalpath/configure.zcml
quintagroup/canonicalpath/interfaces.py
quintagroup/canonicalpath/tests.py
quintagroup/canonicalpath/upgrades.py
quintagroup/canonicalpath/version.txt