Metadata-Version: 1.0
Name: quintagroup.canonicalpath
Version: 0.7
Summary: Brings canonical path calculation functionality
Home-page: http://svn.quintagroup.com/products/quintagroup.canonicalpath
Author: Quintagroup
Author-email: support@quintagroup.com
License: GPL
Keywords: canonical path plone quintagroup
Platform: UNKNOWN
Classifier: Programming Language :: Python
Classifier: Topic :: Software Development :: Libraries :: Python Modules
